grpc_channelz-stubs/METADATA.toml
grpc_channelz-stubs/__init__.pyi
grpc_channelz-stubs/py.typed
grpc_channelz-stubs/v1/__init__.pyi
grpc_channelz-stubs/v1/_async.pyi
grpc_channelz-stubs/v1/_servicer.pyi
grpc_channelz-stubs/v1/channelz.pyi
grpc_channelz-stubs/v1/channelz_pb2.pyi
grpc_channelz-stubs/v1/channelz_pb2_grpc.pyi
types_grpcio_channelz-1.0.0.20250506.dist-info/licenses/LICENSE
types_grpcio_channelz-1.0.0.20250506.dist-info/METADATA
types_grpcio_channelz-1.0.0.20250506.dist-info/WHEEL
types_grpcio_channelz-1.0.0.20250506.dist-info/top_level.txt
types_grpcio_channelz-1.0.0.20250506.dist-info/RECORD
